akridata_akrimanager_v2/__init__.py
akridata_akrimanager_v2/api_client.py
akridata_akrimanager_v2/configuration.py
akridata_akrimanager_v2/exceptions.py
akridata_akrimanager_v2/rest.py
akridata_akrimanager_v2/api/__init__.py
akridata_akrimanager_v2/api/attachment_policies_api.py
akridata_akrimanager_v2/api/auth_api.py
akridata_akrimanager_v2/api/background_catalog_api.py
akridata_akrimanager_v2/api/catalog_api.py
akridata_akrimanager_v2/api/ccs_api.py
akridata_akrimanager_v2/api/cluster_api.py
akridata_akrimanager_v2/api/container_api.py
akridata_akrimanager_v2/api/datagen_api.py
akridata_akrimanager_v2/api/datasets_api.py
akridata_akrimanager_v2/api/de_tools_api.py
akridata_akrimanager_v2/api/default_api.py
akridata_akrimanager_v2/api/ds_jobs_api.py
akridata_akrimanager_v2/api/email_api.py
akridata_akrimanager_v2/api/external_catalog_api.py
akridata_akrimanager_v2/api/groups_api.py
akridata_akrimanager_v2/api/health_api.py
akridata_akrimanager_v2/api/image_api.py
akridata_akrimanager_v2/api/invitations_api.py
akridata_akrimanager_v2/api/jupyterhub_api.py
akridata_akrimanager_v2/api/label_api.py
akridata_akrimanager_v2/api/notifications_api.py
akridata_akrimanager_v2/api/organization_api.py
akridata_akrimanager_v2/api/pipeline_api.py
akridata_akrimanager_v2/api/queries_api.py
akridata_akrimanager_v2/api/repository_api.py
akridata_akrimanager_v2/api/saved_queries_api.py
akridata_akrimanager_v2/api/sms_api.py
akridata_akrimanager_v2/api/subscriptions_api.py
akridata_akrimanager_v2/api/udf_api.py
akridata_akrimanager_v2/api/user_api.py
akridata_akrimanager_v2/api/views_api.py
akridata_akrimanager_v2/api/workflows_api.py
akridata_akrimanager_v2/models/__init__.py
akridata_akrimanager_v2/models/action.py
akridata_akrimanager_v2/models/active_user_response.py
akridata_akrimanager_v2/models/add_columns.py
akridata_akrimanager_v2/models/add_contact.py
akridata_akrimanager_v2/models/add_label_provider.py
akridata_akrimanager_v2/models/add_trusted_org_user.py
akridata_akrimanager_v2-1.23.0.89.dist-info/METADATA
akridata_akrimanager_v2-1.23.0.89.dist-info/WHEEL
akridata_akrimanager_v2-1.23.0.89.dist-info/top_level.txt
akridata_akrimanager_v2-1.23.0.89.dist-info/RECORD
