Metadata-Version: 2.1
Name: akridata_akrimanager_v2
Version: 1.23.0.89
Summary: Akrimanager Backend v2
Home-page: 
Author: OpenAPI Generator community
Author-email: team@openapitools.org
Keywords: OpenAPI,OpenAPI-Generator,Akrimanager Backend v2
Requires-Dist: urllib3>=1.25.3
Requires-Dist: six>=1.10
Requires-Dist: python-dateutil
